{
  "title": "Apothecary diaries",
  "categories": [
    {
      "category": "Season 1",
      "episodes": [
        {
          "title": "Episode 1",
          "src": "https://files.catbox.moe/3qolip.mp4"
        },
        {
          "title": "Episode 2",
          "src": "https://files.catbox.moe/siw5jg.mp4"
        },
        {
          "title": "Episode 3",
          "src": "https://files.catbox.moe/lww0aw.mp4"
        },
        {
          "title": "Episode 4",
          "src": "https://files.catbox.moe/epifd2.mp4"
        },
        {
          "title": "Episode 5",
          "src": "https://files.catbox.moe/hcapbh.mp4"
        },
        {
          "title": "Episode 6",
          "src": "https://files.catbox.moe/9d1mxk.mp4"
        },
        {
          "title": "Episode 7",
          "src": "https://files.catbox.moe/qcp178.mp4"
        },
        {
          "title": "Episode 8",
          "src": "https://files.catbox.moe/3co6rn.mp4"
        },
        {
          "title": "Episode 9",
          "src": "https://files.catbox.moe/68jdab.mp4"
        },
        {
          "title": "Episode 10",
          "src": "https://files.catbox.moe/jb4n9b.mp4"
        },
        {
          "title": "Episode 11",
          "src": "https://files.catbox.moe/qlfqi6.mp4"
        },
        {
          "title": "Episode 12",
          "src": "https://files.catbox.moe/5cvyoa.mp4"
        },
        {
          "title": "Episode 13",
          "src": "https://files.catbox.moe/kdhjxg.mp4"
        },
        {
          "title": "Episode 14",
          "src": "https://files.catbox.moe/umidp9.mp4"
        },
        {
          "title": "Episode 15",
          "src": "https://files.catbox.moe/e93a8e.mp4"
        },
        {
          "title": "Episode 16",
          "src": "https://files.catbox.moe/wat7pc.mp4"
        },
        {
          "title": "Episode 17",
          "src": "https://files.catbox.moe/1qrq4t.mp4"
        },
        {
          "title": "Episode 18",
          "src": "https://files.catbox.moe/3zgp6e.mp4"
        },
        {
          "title": "Episode 19",
          "src": "https://files.catbox.moe/i4qbrs.mp4"
        },
        {
          "title": "Episode 20",
          "src": "https://files.catbox.moe/bykiwq.mp4"
        },
        {
          "title": "Episode 21",
          "src": "https://files.catbox.moe/4i1wzf.mp4"
        },
        {
          "title": "Episode 22",
          "src": "https://files.catbox.moe/q2xiez.mp4"
        },
        {
          "title": "Episode 23",
          "src": "https://files.catbox.moe/iy1fe9.mp4"
        },
        {
          "title": "Episode 24",
          "src": "https://files.catbox.moe/39fb9t.mp4"
        }
      ]
    },
    {
      "category": "Season 2",
      "episodes": [
        {
          "title": "Episode 1",
          "src": "https://files.catbox.moe/f4yepj.mp4"
        },
        {
          "title": "Episode 2",
          "src": "https://files.catbox.moe/v7nf40.mp4"
        },
        {
          "title": "Episode 3",
          "src": "https://files.catbox.moe/ju6j6q.mp4"
        },
        {
          "title": "Episode 4",
          "src": "https://files.catbox.moe/kmnvmv.mp4"
        },
        {
          "title": "Episode 5",
          "src": "https://files.catbox.moe/u4kdwa.mp4"
        },
        {
          "title": "Episode 6",
          "src": "https://files.catbox.moe/97i4r7.mp4"
        },
        {
          "title": "Episode 7",
          "src": "https://files.catbox.moe/9gey1v.mp4"
        },
        {
          "title": "Episode 8",
          "src": "https://files.catbox.moe/slbt40.mp4"
        },
        {
          "title": "Episode 9",
          "src": "https://files.catbox.moe/melf2q.mp4"
        },
        {
          "title": "Episode 10",
          "src": "https://files.catbox.moe/yzg945.mp4"
        },
        {
          "title": "Episode 11",
          "src": "https://files.catbox.moe/f59hgb.mp4"
        },
        {
          "title": "Episode 12",
          "src": "https://files.catbox.moe/htykf4.mp4"
        },
        {
          "title": "Episode 13",
          "src": "https://files.catbox.moe/md56lq.mp4"
        },
        {
          "title": "Episode 14",
          "src": "https://files.catbox.moe/49btuj.mp4"
        },
        {
          "title": "Episode 15",
          "src": "https://files.catbox.moe/d2u5cj.mp4"
        },
        {
          "title": "Episode 16",
          "src": "https://files.catbox.moe/x82bul.mp4"
        },
        {
          "title": "Episode 17",
          "src": "https://files.catbox.moe/4bby51.mp4"
        },
        {
          "title": "Episode 18",
          "src": "https://files.catbox.moe/b3u0wx.mp4"
        },
        {
          "title": "Episode 19",
          "src": "https://files.catbox.moe/h5w8kg.mp4"
        },
        {
          "title": "Episode 20",
          "src": "https://files.catbox.moe/ftbqnm.mp4"
        },
        {
          "title": "Episode 21",
          "src": "https://files.catbox.moe/66xcba.mp4"
        },
        {
          "title": "Episode 22",
          "src": "https://files.catbox.moe/kqkmxv.mp4"
        },
        {
          "title": "Episode 23",
          "src": "https://files.catbox.moe/meg9c0.mp4"
        },
        {
          "title": "Episode 24",
          "src": "https://files.catbox.moe/3vgkhr.mp4"
        }
      ]
    }
  ]
}