{
  "title": "Failure Frame",
  "Image": "https://files.catbox.moe/5kt9mj.jpg",
  "categories": [
    {
      "category": "Season 1",
      "episodes": [
        {
          "title": "Episode 1",
          "src": "https://files.catbox.moe/e1u8r4.mp4"
        },
        {
          "title": "Episode 2",
          "src": "https://files.catbox.moe/f7g2cp.mp4"
        },
        {
          "title": "Episode 3",
          "src": "https://files.catbox.moe/570bl5.mp4"
        },
        {
          "title": "Episode 4",
          "src": "https://files.catbox.moe/zmqbqp.mp4"
        },
        {
          "title": "Episode 5",
          "src": "https://files.catbox.moe/qhcjg8.mp4"
        },
        {
          "title": "Episode 6",
          "src": "https://files.catbox.moe/bdx1aj.mp4"
        },
        {
          "title": "Episode 7",
          "src": "https://files.catbox.moe/rgg6fu.mp4"
        },
        {
          "title": "Episode 8",
          "src": "https://files.catbox.moe/f2x24u.mp4"
        },
        {
          "title": "Episode 9",
          "src": "https://files.catbox.moe/tqx1ba.mp4"
        },
        {
          "title": "Episode 10",
          "src": "https://files.catbox.moe/oqtr8e.mp4"
        },
        {
          "title": "Episode 11",
          "src": "https://files.catbox.moe/nqn6te.mp4"
        },
        {
          "title": "Episode 12",
          "src": "https://files.catbox.moe/z9zeoc.mp4"
        }
      ]
    }
  ],
  "LatestTime": "2025-08-14T04:14:14.591Z"
}