{
  "title": "You And I Are Polar Opposites",
  "Image": "https://i.animepahe.si/posters/2c1068e3f59d77254be3c75ff4131567ea1e05c02d27e81154e9c2db4445e53a.jpg",
  "LatestTime": "2026-03-16T02:14:40.800Z",
  "categories": [
    {
      "category": "Season 1",
      "episodes": [
        {
          "title": "Episode 01",
          "src": "https://cpr.xpbliss.fyi/pub/MM/S01E01_Episode_1.mp4",
          "fileSizeBytes": 145972049,
          "durationSeconds": 1447
        },
        {
          "title": "Episode 02",
          "src": "https://cpr.xpbliss.fyi/pub/MM/S01E02_Episode_2.mp4",
          "fileSizeBytes": 154769363,
          "durationSeconds": 1447
        },
        {
          "title": "Episode 3",
          "src": "https://cpr.xpbliss.fyi/pub/MM/S01E03_Episode_3.mp4",
          "fileSizeBytes": 130896008,
          "durationSeconds": 1447
        },
        {
          "title": "Episode 4",
          "src": "https://cpr.xpbliss.fyi/pub/MM/DontTouchPls/S01E04_Episode_4.mp4",
          "fileSizeBytes": 140760696,
          "durationSeconds": 1447
        },
        {
          "title": "Episode 5",
          "src": "https://cpr.xpbliss.fyi/pub/MM/DontTouchPls/S01E05_Episode_5.mp4",
          "fileSizeBytes": 123498957,
          "durationSeconds": 1447
        },
        {
          "title": "Episode 6",
          "src": "https://cpr.xpbliss.fyi/pub/MM/S01E06_Episode_6.mp4",
          "fileSizeBytes": 122517548,
          "durationSeconds": 1447
        },
        {
          "title": "Episode 7",
          "src": "https://cpr.xpbliss.fyi/pub/MM/S01E07_Episode_7.mp4",
          "fileSizeBytes": 133353225,
          "durationSeconds": 1432
        },
        {
          "title": "Episode 8",
          "src": "https://cpr.xpbliss.fyi/pub/MM/DontTouchPls/S01E08_Episode_8.mp4-1773626967.573806-_VQO1ALa.mp4",
          "fileSizeBytes": 131373861,
          "durationSeconds": 1432
        },
        {
          "title": "Episode 9",
          "src": "https://cpr.xpbliss.fyi/pub/MM/DontTouchPls/S01E09_Episode_9.mp4",
          "fileSizeBytes": 122053340,
          "durationSeconds": 1432
        }
      ]
    }
  ],
  "totalFileSizeBytes": 1205195047,
  "totalDurationSeconds": 12978
}